pybmdope/__init__.py
pybmdope/bmdope.py
pybmdope/key.py
pybmdope/metadata.py
pybmdope/util.py
pybmdope-1.1.3.dist-info/licenses/LICENSE
pybmdope-1.1.3.dist-info/METADATA
pybmdope-1.1.3.dist-info/WHEEL
pybmdope-1.1.3.dist-info/top_level.txt
pybmdope-1.1.3.dist-info/RECORD
